{"cameraMode":{"drawMode":0,"name":"Shaded","section":"Shading Mode"},"sceneLighting":false,"audioPlay":false,"sceneViewState":{"m_AlwaysRefresh":false,"showFog":true,"showSkybox":false,"showFlares":true,"showImageEffects":true,"showParticleSystems":true,"showVisualEffectGraphs":true,"m_FxEnabled":true},"in2DMode":false,"pivot":{"x":-1.3448796272277833,"y":2.0,"z":15.012999534606934},"rotation":{"x":0.15669342875480653,"y":-0.437857061624527,"z":0.07773343473672867,"w":0.8819221258163452},"size":2.020519256591797,"orthographic":false}